{
  "minecraft:recipes/decorations/crafting_table": {
    "criteria": {
      "unlock_right_away": "2023-08-03 21:50:40 +0800"
    },
    "done": true
  },
  "minecraft:adventure/adventuring_time": {
    "criteria": {
      "minecraft:frozen_river": "2023-08-03 21:50:49 +0800",
      "minecraft:snowy_plains": "2023-08-03 21:50:41 +0800",
      "minecraft:snowy_taiga": "2023-08-05 13:27:03 +0800"
    },
    "done": false
  },
  "minecraft:recipes/transportation/mangrove_boat": {
    "criteria": {
      "in_water": "2023-08-05 13:27:28 +0800"
    },
    "done": true
  },
  "minecraft:recipes/transportation/acacia_boat": {
    "criteria": {
      "in_water": "2023-08-05 13:27:28 +0800"
    },
    "done": true
  },
  "minecraft:recipes/transportation/cherry_boat": {
    "criteria": {
      "in_water": "2023-08-05 13:27:28 +0800"
    },
    "done": true
  },
  "minecraft:recipes/transportation/bamboo_raft": {
    "criteria": {
      "in_water": "2023-08-05 13:27:28 +0800"
    },
    "done": true
  },
  "minecraft:recipes/transportation/spruce_boat": {
    "criteria": {
      "in_water": "2023-08-05 13:27:28 +0800"
    },
    "done": true
  },
  "minecraft:recipes/transportation/birch_boat": {
    "criteria": {
      "in_water": "2023-08-05 13:27:28 +0800"
    },
    "done": true
  },
  "minecraft:recipes/transportation/oak_boat": {
    "criteria": {
      "in_water": "2023-08-05 13:27:28 +0800"
    },
    "done": true
  },
  "minecraft:recipes/transportation/jungle_boat": {
    "criteria": {
      "in_water": "2023-08-05 13:27:28 +0800"
    },
    "done": true
  },
  "minecraft:recipes/transportation/dark_oak_boat": {
    "criteria": {
      "in_water": "2023-08-05 13:27:28 +0800"
    },
    "done": true
  },
  "minecraft:recipes/building_blocks/packed_ice": {
    "criteria": {
      "has_ice": "2023-08-11 12:11:37 +0800"
    },
    "done": true
  },
  "minecraft:recipes/misc/creeper_banner_pattern": {
    "criteria": {
      "has_creeper_head": "2023-08-17 15:51:40 +0800"
    },
    "done": true
  },
  "minecraft:recipes/building_blocks/quartz_stairs": {
    "criteria": {
      "has_quartz_block": "2023-08-17 15:53:13 +0800"
    },
    "done": true
  },
  "minecraft:recipes/building_blocks/smooth_quartz": {
    "criteria": {
      "has_quartz_block": "2023-08-17 15:53:13 +0800"
    },
    "done": true
  },
  "minecraft:recipes/building_blocks/quartz_slab": {
    "criteria": {
      "has_quartz_block": "2023-08-17 15:53:13 +0800"
    },
    "done": true
  },
  "minecraft:recipes/building_blocks/chiseled_quartz_block": {
    "criteria": {
      "has_quartz_block": "2023-08-17 15:53:13 +0800"
    },
    "done": true
  },
  "minecraft:recipes/building_blocks/quartz_bricks": {
    "criteria": {
      "has_quartz_block": "2023-08-17 15:53:13 +0800"
    },
    "done": true
  },
  "minecraft:recipes/building_blocks/quartz_bricks_from_quartz_block_stonecutting": {
    "criteria": {
      "has_quartz_block": "2023-08-17 15:53:13 +0800"
    },
    "done": true
  },
  "minecraft:recipes/building_blocks/chiseled_quartz_block_from_quartz_block_stonecutting": {
    "criteria": {
      "has_quartz_block": "2023-08-17 15:53:13 +0800"
    },
    "done": true
  },
  "minecraft:recipes/building_blocks/quartz_pillar_from_quartz_block_stonecutting": {
    "criteria": {
      "has_quartz_block": "2023-08-17 15:53:13 +0800"
    },
    "done": true
  },
  "minecraft:recipes/building_blocks/quartz_slab_from_stonecutting": {
    "criteria": {
      "has_quartz_block": "2023-08-17 15:53:13 +0800"
    },
    "done": true
  },
  "minecraft:recipes/building_blocks/quartz_pillar": {
    "criteria": {
      "has_quartz_block": "2023-08-17 15:53:13 +0800"
    },
    "done": true
  },
  "minecraft:recipes/building_blocks/quartz_stairs_from_quartz_block_stonecutting": {
    "criteria": {
      "has_quartz_block": "2023-08-17 15:53:13 +0800"
    },
    "done": true
  },
  "DataVersion": 3465
}